{
  "건치연혁": "본래 고려의 요원군(遼原郡)이었다. 장덕진(長德鎭)이라고도 하였다. 목종(穆宗) 4년에 덕주 방어사(德州防禦使)라 일컬었고, 원종(元宗) 원년에는 몽고병을 피하여 안주(安州)의 노도(蘆島)로 들어간 뒤에 모두 다섯 번이나 옮겼으며, 충렬왕 6년에 이르러 옛 땅으로 돌아와 성주(成州)에 속하였다가, 공민왕 20년에 갈라져 지주사(知州事)로 되었다. 본조 태종 13년에 지금의 이름으로 고치고, 얼마 되지 않아 맹산현(孟山縣)으로 일컫다가, 15년에 맹산을 다시 두면서 덕천군으로 승격하였다.\n",
  "관원": "군수(郡守)ㆍ훈도(訓導) 각 1인.\n\n",
  "군명": "요원(遼原)ㆍ장덕(長德)ㆍ덕주(德州)\n",
  "성씨": "본군 오(吳) 영일(迎日). 방(邦) 청송(靑松). 문(文) 해주(海州). 김(金)ㆍ동(童)ㆍ노(盧) 모두 재령(載寧). 변(邊) 이산(伊山). 최(崔) 연산(連山)\n\n",
  "형승": "땅이 향산(香山)에 닿아 있다. 강이 큰 바다로 통한다. 박은(朴訔)의 시가 있다.\n\n",
  "산천": "장안산(長安山) 군의 남쪽 25리에 있는 진산이다. 당산(堂山) 군의 북쪽 3리에 있다. 남산(南山) 군의 남쪽 4리에 있다. 금성산(金城山) 군의 동쪽 20리에 있다. 장양산(長楊山) 군의 남쪽 25리에 있다. 향산(香山) 군의 북쪽 45리에 있는데, 곧 영변부의 묘향산(妙香山)이다. 관음산(觀音山) 군의 북쪽 48리에 있다. 삼탄(三灘) 군의 동쪽 15리에 있는데 영원과 맹산의 물이 이곳에 이르러 교류하므로 삼탄이라고 한다. 여울가에 굴이 있고 굴 속에 못이 있는데, 그 깊이를 헤아릴 수 없다. 날씨가 가물 때에 범의 머리를 담그면 비가 내린다. 응강(凝江) 군의 남쪽 2리에 있는데 근원은 영원군에서 나와 비류강과 합류하여 대동강(大同江)으로 들어간다. 막탄(瘼灘) 군의 남쪽 30리에 있는데 맹산현 대천(大川)의 하류로서 또 삼탄으로 들어간다.\n\n",
  "토산": "옻[漆]ㆍ회양목[黃楊]ㆍ쏘가리[錦鱗魚]\n",
  "성곽": "금성(金城) 금성산(金城山)에 있는데 산의 이름이 금성산이 된 것은 이 성 때문이다. 본조 태조 때에 돌로 쌓았는데, 삼면이 낭떠러지이고, 둘레가 3천 1백 25척, 높이가 8척이다. 안에 샘이 하나 있으며, 또 군창(軍倉)이 있다.\n\n",
  "학교": "향교 군의 서쪽 7리에 있다.\n\n",
  "원우": "평지원(平地院) 군의 서쪽 40리에 있다.\n\n",
  "불우": "관음사(觀音寺) 관음산에 있다. 흥덕사(興德寺) 장안산(長安山)에 있다.\n\n",
  "사묘": "사직단 군의 서쪽에 있다. 문묘 향교에 있다. 성황사 당산(堂山)에 있다. 여단 군의 북쪽에 있다.\n\n",
  "고적": "옛 무산현[古撫山縣] 군의 서쪽 1백 80리에 있다. 예전에도 영변부에 속해 있었는데, 우리 세조 때에 내속시켰다. 자세한 것은 영변부 연혁조에 있다.\n\n",
  "명환": "본조 박명산(朴命山) 군수가 되었을 때 흉년을 만나서 자기의 집에서 갖다가 생활하였다. 백성들이 지금에 이르도록 칭송하고 있다.\n\n",
  "제영": "질펀한 긴 강은 외로운 성을 끌어안았는데 안숭선(安崇善)의 시에, “질펀한 긴 강은 외로운 성을 끌어안고, 넓고 깊숙한 골짜기는 한결같이 평평하네.” 하였다. 풍년 들고 사람이 화목하여 의로운 군사를 기른다. 박은(朴訔)의 시에, “관청은 한가롭고 일은 간소하니 가혹한 정치가 없고, 풍년들고 사람이 화목하여 의로운 군사를 기르네.” 하였다.『신증』 사면의 산은 둘러 겹성을 만들었고 성현(成俔)의 시에, “사면의 산은 싸고 둘러 겹성을 만들었고, 들은 넓고 넓어 손바닥같이 평평하구나. 나무 그림자 봄을 간직하였는데 꽃은 벌써 졌고, 시냇물은 돌을 부딪쳐 맑기만 하네. 주진촌(朱陳村)의 순박한 풍속 백성들은 모두 생업을 편안히 하고, 변방 거칠은 땅에는 전쟁을 알지 못하여, 교화를 베풀어 끼친 은택 조금도 없으나, 다만 마음과 힘을 가지고 나의 정성을 다하리라.” 하였다.\n\n《대동지지(大東地志)》\n",
  "방면": "군내(郡內) 남쪽으로 20리이다. 고척(古尺) 동북쪽으로 60리이다. 삼탄(三灘) 동남쪽으로 30리이다. 고리항(古里項) 서북쪽으로 45리이다. 서초소(西初所) 서쪽으로 15리이다. 이소(二所) 30리이다. 송산(松山) 45리이다. 동면 30리이다. 남면 30리이다.\n\n",
  "영아": "청남우영(淸南右營) 영장(營將)이 1명인데 본군 군수가 겸하였다. ○ 속읍은 덕천ㆍ자산(慈山)ㆍ영원(寧遠)ㆍ개천(价川)ㆍ맹산(孟山)ㆍ은산이다.\n\n",
  "창고": "읍창ㆍ서창 25리이다. 읍서창(邑西倉) 15리이다. 남창 28리이다. 신창 북쪽으로 25리이다. 송창(松倉) 북쪽으로 50리이다. 금성창(金城倉) 동쪽으로 27리, 금성 내에 있다. 읍신창(邑新倉) 서남쪽으로 10리이다. 내송창(內松倉) 북쪽으로 60리이다. 장림창(長林倉) 북쪽으로 30리이다.\n\n",
  "진도": "요원강진(遼原江津) 군의 남쪽이다. 고성강진(古城江津) 동쪽으로 35리인데 영원으로 통한다.\n\n",
  "교량": "시량천교(矢梁川橋) 서쪽으로 10리 지점에 있다. 유장교(楡長橋) 서쪽으로 20리 지점에 있다. 장림천교(長林川橋) 북쪽으로 15리 지점에 있다. 신창교(新倉橋) 북쪽으로 20리 지점에 있다.\n\n",
  "누정": "힐융정(詰戎亭) 서쪽으로 2리, 강변에 있다. 선유정(仙遊亭) 읍내에 있다. 망일루(望日樓) 읍내에 있다.\n\n\n\t\t\n\t\n\t\n\t\n\t\n\t\t\n\n\t\t\n\n\t\t\n[주-D001] 주진촌(朱陳村) : \n중국 서주(徐州) 땅에 주진촌이 있어, 주씨와 진씨가 사이좋게 지내고 풍속이 순후하였다고 한다.\n\n\n\t\n\t\n\t\t\n\t\n\t\tⓒ 한국고전번역원 | 이익성 (역) | 1970\n    \n\t\n"
}